{
    "plugin_definitions": [
        {
            "name": "win32",
            "interface": "window",
            "path": "./window_win32.dll"
        },
        {
            "name": "default",
            "interface": "gui_application",
            "path": "./gui_application_default.dll"
        },
        {
            "name": "default",
            "interface": "input",
            "path": "./input_default.dll"
        },
        {
            "name": "default",
            "interface": "draw",
            "path": "./draw_default.dll"
        }
    ]
}